coastsat/SDS_classify.py
coastsat/SDS_download.py
coastsat/SDS_preprocess.py
coastsat/SDS_shoreline.py
coastsat/SDS_tools.py
coastsat/SDS_transects.py
coastsat/__init__.py
coastsat/gdal_merge.py
coastsat/classification/__int__.py
coastsat/classification/models/NN_4classes_Landsat.pkl
coastsat/classification/models/NN_4classes_Landsat_bright.pkl
coastsat/classification/models/NN_4classes_Landsat_bright_new.pkl
coastsat/classification/models/NN_4classes_Landsat_dark.pkl
coastsat/classification/models/NN_4classes_Landsat_dark_new.pkl
coastsat/classification/models/NN_4classes_Landsat_new.pkl
coastsat/classification/models/NN_4classes_S2.pkl
coastsat/classification/models/NN_4classes_S2_new.pkl
coastsat/classification/models/__init__.py
coastsat/classification/training_data/CoastSat_training_set_L8.pkl
coastsat/classification/training_data/CoastSat_training_set_S2.pkl
coastsat/classification/training_data/__init__.py
coastsat/classification/training_sites/BYRON.kml
coastsat/classification/training_sites/NEWCASTLE.kml
coastsat/classification/training_sites/SAWTELL.kml
coastsat/classification/training_sites/__init__.py
pkg_toml_test_2320sharon-0.0.30.dist-info/LICENSE.md
pkg_toml_test_2320sharon-0.0.30.dist-info/METADATA
pkg_toml_test_2320sharon-0.0.30.dist-info/WHEEL
pkg_toml_test_2320sharon-0.0.30.dist-info/top_level.txt
pkg_toml_test_2320sharon-0.0.30.dist-info/RECORD
