Metadata-Version: 2.1
Name: pkg-toml-test-2320sharon
Version: 0.0.30
Summary: A Global shoreline mapping tool from satellite imagery
Author: Kilian Vos
Author-email: Sharon Fitzpatrick <sharon.fitzpatrick23@gmail.com>
Project-URL: Homepage, https://github.com/kvos/CoastSat
Project-URL: Bug Tracker, https://github.com/kvos/CoastSat/issues
Classifier: Programming Language :: Python :: 3
Classifier: License :: OSI Approved :: MIT License
Classifier: Operating System :: OS Independent
Requires-Python: >=3.8
License-File: LICENSE.md
Requires-Dist: scikit-image
Requires-Dist: earthengine-api (>=0.1.304)
Requires-Dist: matplotlib
Requires-Dist: astropy
Requires-Dist: notebook
Requires-Dist: pyqt5
Requires-Dist: scipy
Requires-Dist: numpy (<1.23.0)
